pysandbox/__init__.py
pysandbox/main.py
pysandbox/Util/__init__.py
pysandbox/Util/conn.py
pysandbox/Util/log.py
pysandbox/Util/reshape.py
pysandbox/config/__init__.py
pysandbox/config/default.py
pysandbox/cst/__init__.py
pysandbox/data/__init__.py
pysandbox/data/dataset.py
pysandbox/data/getData.py
pysandbox/math/__init__.py
pysandbox/models/AlexNet.py
pysandbox/models/BasicModule.py
pysandbox/models/ResNet34.py
pysandbox/models/__init__.py
pysandbox/stat/__init__.py
pywulai/__init__.py
pywulai/aibot.py
pywulai/data.py
pywulai/deeplearn.py
pywulai/dialog.py
pywulai/global.py
pywulai/kmbase.py
pywulai/kms.py
pywulai/model.py
pywulai/multiple.py
pywulai/nlp.py
pywulai/plan.py
pywulai/schedule.py
pywulai/task.py
pysandbox-1.0.0.dist-info/LICENSE
pysandbox-1.0.0.dist-info/METADATA
pysandbox-1.0.0.dist-info/WHEEL
pysandbox-1.0.0.dist-info/top_level.txt
pysandbox-1.0.0.dist-info/RECORD
