Metadata-Version: 2.1
Name: pysandbox
Version: 1.0.0
Summary: reshape data wu lai open api in py language 
Home-page: http://www.reshapedata.com
Author: Reshapedata
Author-email: hulilei@takewiki.com.cn
License: Apache License
Keywords: reshapedata,pysandbox
Platform: UNKNOWN
Requires-Python: >=3.6
Requires-Dist: requests
